{"data":[{"files":[{"expansions":[],"filename":"/Users/madslun/Documents/Programmering/U_look_stunning/stun/Message.cpp","segments":[[7,35,0,true,true],[9,2,0,false,false],[11,38,1,true,true],[13,2,0,false,false],[15,37,0,true,true],[17,2,0,false,false],[19,42,1,true,true],[21,2,0,false,false],[23,37,1,true,true],[25,2,0,false,false],[27,42,1,true,true],[29,2,0,false,false],[31,51,0,true,true],[33,2,0,false,false],[35,45,0,true,true],[37,2,0,false,false],[39,58,1,true,true],[41,2,0,false,false],[43,48,0,true,true],[45,2,0,false,false],[47,40,0,true,true],[49,2,0,false,false],[51,48,0,true,true],[53,2,0,false,false],[55,47,0,true,true],[57,2,0,false,false],[59,46,0,true,true],[61,2,0,false,false],[63,60,0,true,true],[65,2,0,false,false],[67,53,0,true,true],[69,2,0,false,false],[71,48,0,true,true],[73,2,0,false,false],[75,64,0,true,true],[77,2,0,false,false],[79,42,0,true,true],[81,2,0,false,false],[83,52,0,true,true],[85,2,0,false,false],[87,51,0,true,true],[89,2,0,false,false],[91,48,4,true,true],[93,2,0,false,false]],"summary":{"functions":{"count":22,"covered":6,"percent":27.27272727272727},"instantiations":{"count":22,"covered":6,"percent":27.27272727272727},"lines":{"count":66,"covered":18,"percent":27.27272727272727},"regions":{"count":22,"covered":6,"notcovered":16,"percent":27.27272727272727}}},{"expansions":[],"filename":"/Users/madslun/Documents/Programmering/U_look_stunning/stun/Responder.cpp","segments":[[10,60,1,true,true],[21,2,0,false,false],[23,45,0,true,true],[25,2,0,false,false],[27,78,0,true,true],[28,20,0,true,true],[28,25,0,true,false],[28,27,0,true,true],[28,30,0,true,false],[28,32,0,true,true],[30,6,0,true,false],[31,2,0,false,false],[33,47,1,true,true],[44,20,5,true,true],[44,25,1,true,false],[44,27,4,true,true],[44,30,1,true,false],[44,31,4,true,false],[44,32,4,true,true],[46,6,1,true,false],[69,2,0,false,false],[71,48,0,true,true],[73,2,0,false,false],[75,52,0,true,true],[77,2,0,false,false],[79,50,0,true,true],[81,2,0,false,false]],"summary":{"functions":{"count":7,"covered":2,"percent":28.571428571428569},"instantiations":{"count":7,"covered":2,"percent":28.571428571428569},"lines":{"count":66,"covered":49,"percent":74.242424242424249},"regions":{"count":13,"covered":5,"notcovered":8,"percent":38.461538461538467}}},{"expansions":[],"filename":"/Users/madslun/Documents/Programmering/U_look_stunning/stun/main.cpp","segments":[[71,45,1,true,true],[75,9,1,true,true],[75,15,1,true,false],[76,9,1,true,true],[76,20,0,true,false],[77,5,0,true,true],[78,2,0,false,false],[87,82,0,true,true],[91,21,0,true,true],[91,26,0,true,false],[91,28,0,true,true],[91,31,0,true,false],[91,33,0,true,true],[93,6,0,true,false],[101,27,0,true,true],[102,13,0,true,true],[102,31,0,true,false],[103,13,0,true,true],[103,24,0,true,false],[106,5,0,true,true],[106,17,0,true,false],[107,2,0,false,false],[110,83,0,true,true],[112,2,0,false,false],[115,100,0,true,true],[130,21,0,true,true],[130,27,0,true,false],[130,29,0,true,true],[130,32,0,true,false],[130,34,0,true,true],[132,6,0,true,false],[140,2,0,false,false],[147,83,0,true,true],[154,12,0,true,true],[154,13,0,true,false],[154,15,0,true,true],[161,23,0,true,false],[162,13,0,true,true],[164,21,0,true,true],[164,60,0,true,false],[164,62,0,true,true],[171,18,0,true,false],[175,13,0,true,true],[180,22,0,true,false],[183,13,0,true,true],[185,22,0,true,false],[189,13,0,true,true],[192,47,0,true,false],[193,21,0,true,true],[193,42,0,true,false],[199,13,0,true,true],[201,22,0,true,false],[230,2,0,false,false],[240,61,1,true,true],[252,9,1,true,true],[252,14,1,true,false],[252,18,1,true,true],[252,27,1,true,false],[252,28,0,true,false],[252,29,0,true,true],[255,6,1,true,false],[258,5,1,true,true],[261,9,1,true,true],[261,33,1,true,false],[261,34,0,true,false],[261,35,0,true,true],[263,6,1,true,false],[268,5,1,true,true],[274,21,4,true,true],[274,26,1,true,false],[274,28,3,true,true],[274,31,1,true,false],[274,32,3,true,false],[274,33,3,true,true],[276,6,1,true,false],[278,9,1,true,true],[278,44,1,true,false],[278,45,0,true,false],[278,46,0,true,true],[281,6,1,true,false],[283,5,1,true,true],[302,2,0,false,false],[311,62,2,true,true],[318,2,0,false,false],[327,62,4,true,true],[335,2,0,false,false],[344,60,0,true,true],[347,2,0,false,false],[350,12,1,true,true],[409,2,0,false,false]],"summary":{"functions":{"count":10,"covered":5,"percent":50},"instantiations":{"count":10,"covered":5,"percent":50},"lines":{"count":286,"covered":138,"percent":48.251748251748253},"regions":{"count":47,"covered":18,"notcovered":29,"percent":38.297872340425535}}}],"functions":[{"count":1,"filenames":["/Users/madslun/Documents/Programmering/U_look_stunning/stun/main.cpp"],"name":"_ZN6Reader13cookieCheckerEj","regions":[[71,45,78,2,1,0,0,0],[75,9,75,15,1,0,0,0],[75,16,76,9,1,0,0,3],[76,9,76,20,1,0,0,0],[76,20,77,5,0,0,0,3],[77,5,78,2,0,0,0,0]]},{"count":0,"filenames":["/Users/madslun/Documents/Programmering/U_look_stunning/stun/main.cpp"],"name":"_ZN6Reader13checkUsernameERNSt3__16vectorIhNS0_9allocatorIhEEEEt","regions":[[87,82,107,2,0,0,0,0],[91,21,91,26,0,0,0,0],[91,28,91,31,0,0,0,0],[91,32,91,33,0,0,0,3],[91,33,93,6,0,0,0,0],[101,26,101,27,0,0,0,3],[101,27,104,6,0,0,0,0],[102,13,102,31,0,0,0,0],[102,32,103,13,0,0,0,3],[103,13,103,24,0,0,0,0],[106,5,106,17,0,0,0,0]]},{"count":0,"filenames":["/Users/madslun/Documents/Programmering/U_look_stunning/stun/main.cpp"],"name":"_ZN6Reader14checkMsgIngrtyERNSt3__16vectorIhNS0_9allocatorIhEEEEt","regions":[[110,83,112,2,0,0,0,0]]},{"count":0,"filenames":["/Users/madslun/Documents/Programmering/U_look_stunning/stun/main.cpp"],"name":"_ZN6Reader14checkXorMappedERNSt3__16vectorIhNS0_9allocatorIhEEEEtj","regions":[[115,100,140,2,0,0,0,0],[130,21,130,27,0,0,0,0],[130,29,130,32,0,0,0,0],[130,33,130,34,0,0,0,3],[130,34,132,6,0,0,0,0]]},{"count":0,"filenames":["/Users/madslun/Documents/Programmering/U_look_stunning/stun/main.cpp"],"name":"_ZN6Reader14messageCheckerERNSt3__16vectorIhNS0_9allocatorIhEEEE7Message","regions":[[147,83,230,2,0,0,0,0],[154,12,154,13,0,0,0,0],[154,14,154,15,0,0,0,3],[154,15,204,6,0,0,0,0],[161,23,202,14,0,0,0,3],[162,13,172,22,0,0,0,0],[164,21,164,60,0,0,0,0],[164,61,164,62,0,0,0,3],[164,62,171,18,0,0,0,0],[175,13,180,22,0,0,0,0],[183,13,185,22,0,0,0,0],[189,13,196,22,0,0,0,0],[192,47,193,21,0,0,0,3],[193,21,193,42,0,0,0,0],[199,13,201,22,0,0,0,0]]},{"count":1,"filenames":["/Users/madslun/Documents/Programmering/U_look_stunning/stun/main.cpp"],"name":"_ZN6Reader12validateDataEPhj","regions":[[240,61,302,2,1,0,0,0],[252,9,252,14,1,0,0,0],[252,9,252,27,1,0,0,0],[252,18,252,27,1,0,0,0],[252,28,252,29,0,0,0,3],[252,29,255,6,0,0,0,0],[255,6,258,5,1,0,0,3],[258,5,302,2,1,0,0,0],[261,9,261,33,1,0,0,0],[261,34,261,35,0,0,0,3],[261,35,263,6,0,0,0,0],[263,6,268,5,1,0,0,3],[268,5,302,2,1,0,0,0],[274,21,274,26,4,0,0,0],[274,28,274,31,3,0,0,0],[274,32,274,33,3,0,0,3],[274,33,276,6,3,0,0,0],[278,9,278,44,1,0,0,0],[278,45,278,46,0,0,0,3],[278,46,281,6,0,0,0,0],[281,6,283,5,1,0,0,3],[283,5,302,2,1,0,0,0]]},{"count":2,"filenames":["/Users/madslun/Documents/Programmering/U_look_stunning/stun/main.cpp"],"name":"_ZN6Reader6read16ERNSt3__16vectorIhNS0_9allocatorIhEEEE","regions":[[311,62,318,2,2,0,0,0]]},{"count":4,"filenames":["/Users/madslun/Documents/Programmering/U_look_stunning/stun/main.cpp"],"name":"_ZN6Reader6read32ERNSt3__16vectorIhNS0_9allocatorIhEEEE","regions":[[327,62,335,2,4,0,0,0]]},{"count":0,"filenames":["/Users/madslun/Documents/Programmering/U_look_stunning/stun/main.cpp"],"name":"_ZN6Reader5read8ERNSt3__16vectorIhNS0_9allocatorIhEEEE","regions":[[344,60,347,2,0,0,0,0]]},{"count":1,"filenames":["/Users/madslun/Documents/Programmering/U_look_stunning/stun/main.cpp"],"name":"main","regions":[[350,12,409,2,1,0,0,0]]},{"count":0,"filenames":["/Users/madslun/Documents/Programmering/U_look_stunning/stun/Message.cpp"],"name":"_ZNK7Message7getTypeEv","regions":[[7,35,9,2,0,0,0,0]]},{"count":1,"filenames":["/Users/madslun/Documents/Programmering/U_look_stunning/stun/Message.cpp"],"name":"_ZN7Message7setTypeEt","regions":[[11,38,13,2,1,0,0,0]]},{"count":0,"filenames":["/Users/madslun/Documents/Programmering/U_look_stunning/stun/Message.cpp"],"name":"_ZNK7Message9getLengthEv","regions":[[15,37,17,2,0,0,0,0]]},{"count":1,"filenames":["/Users/madslun/Documents/Programmering/U_look_stunning/stun/Message.cpp"],"name":"_ZN7Message9setLengthEt","regions":[[19,42,21,2,1,0,0,0]]},{"count":1,"filenames":["/Users/madslun/Documents/Programmering/U_look_stunning/stun/Message.cpp"],"name":"_ZNK7Message9getCookieEv","regions":[[23,37,25,2,1,0,0,0]]},{"count":1,"filenames":["/Users/madslun/Documents/Programmering/U_look_stunning/stun/Message.cpp"],"name":"_ZN7Message9setCookieEj","regions":[[27,42,29,2,1,0,0,0]]},{"count":0,"filenames":["/Users/madslun/Documents/Programmering/U_look_stunning/stun/Message.cpp"],"name":"_ZNK7Message16getTransactionIdEv","regions":[[31,51,33,2,0,0,0,0]]},{"count":0,"filenames":["/Users/madslun/Documents/Programmering/U_look_stunning/stun/Message.cpp"],"name":"_ZNK7Message17getSoftwareHeaderEv","regions":[[35,45,37,2,0,0,0,0]]},{"count":1,"filenames":["/Users/madslun/Documents/Programmering/U_look_stunning/stun/Message.cpp"],"name":"_ZN7Message17setSoftwareHeaderEj","regions":[[39,58,41,2,1,0,0,0]]},{"count":0,"filenames":["/Users/madslun/Documents/Programmering/U_look_stunning/stun/Message.cpp"],"name":"_ZNK7Message13getServerNameEv","regions":[[43,48,45,2,0,0,0,0]]},{"count":0,"filenames":["/Users/madslun/Documents/Programmering/U_look_stunning/stun/Message.cpp"],"name":"_ZNK7Message12getXorHeaderEv","regions":[[47,40,49,2,0,0,0,0]]},{"count":0,"filenames":["/Users/madslun/Documents/Programmering/U_look_stunning/stun/Message.cpp"],"name":"_ZN7Message12setXorHeaderEj","regions":[[51,48,53,2,0,0,0,0]]},{"count":0,"filenames":["/Users/madslun/Documents/Programmering/U_look_stunning/stun/Message.cpp"],"name":"_ZNK7Message12getXorAdressEv","regions":[[55,47,57,2,0,0,0,0]]},{"count":0,"filenames":["/Users/madslun/Documents/Programmering/U_look_stunning/stun/Message.cpp"],"name":"_ZNK7Message18getIntegrityHeaderEv","regions":[[59,46,61,2,0,0,0,0]]},{"count":0,"filenames":["/Users/madslun/Documents/Programmering/U_look_stunning/stun/Message.cpp"],"name":"_ZN7Message18setIntegrityHeaderEj","regions":[[63,60,65,2,0,0,0,0]]},{"count":0,"filenames":["/Users/madslun/Documents/Programmering/U_look_stunning/stun/Message.cpp"],"name":"_ZNK7Message18getHmacFingerprintEv","regions":[[67,53,69,2,0,0,0,0]]},{"count":0,"filenames":["/Users/madslun/Documents/Programmering/U_look_stunning/stun/Message.cpp"],"name":"_ZNK7Message20getFingerprintHeaderEv","regions":[[71,48,73,2,0,0,0,0]]},{"count":0,"filenames":["/Users/madslun/Documents/Programmering/U_look_stunning/stun/Message.cpp"],"name":"_ZN7Message20setFingerprintHeaderEj","regions":[[75,64,77,2,0,0,0,0]]},{"count":0,"filenames":["/Users/madslun/Documents/Programmering/U_look_stunning/stun/Message.cpp"],"name":"_ZNK7Message14getFingerprintEv","regions":[[79,42,81,2,0,0,0,0]]},{"count":0,"filenames":["/Users/madslun/Documents/Programmering/U_look_stunning/stun/Message.cpp"],"name":"_ZN7Message14setFingerprintEj","regions":[[83,52,85,2,0,0,0,0]]},{"count":0,"filenames":["/Users/madslun/Documents/Programmering/U_look_stunning/stun/Message.cpp"],"name":"_ZN7Message16setTransactionIdEji","regions":[[87,51,89,2,0,0,0,0]]},{"count":4,"filenames":["/Users/madslun/Documents/Programmering/U_look_stunning/stun/Message.cpp"],"name":"_ZN7Message13setServerNameEji","regions":[[91,48,93,2,4,0,0,0]]},{"count":1,"filenames":["/Users/madslun/Documents/Programmering/U_look_stunning/stun/Responder.cpp"],"name":"_ZN9Responder12buildMessageEPj","regions":[[10,60,21,2,1,0,0,0]]},{"count":0,"filenames":["/Users/madslun/Documents/Programmering/U_look_stunning/stun/Responder.cpp"],"name":"_ZN9Responder9setHeaderER7Message","regions":[[23,45,25,2,0,0,0,0]]},{"count":0,"filenames":["/Users/madslun/Documents/Programmering/U_look_stunning/stun/Responder.cpp"],"name":"_ZN9Responder16setTransactionIdER7MessagePj","regions":[[27,78,31,2,0,0,0,0],[28,20,28,25,0,0,0,0],[28,27,28,30,0,0,0,0],[28,31,28,32,0,0,0,3],[28,32,30,6,0,0,0,0]]},{"count":1,"filenames":["/Users/madslun/Documents/Programmering/U_look_stunning/stun/Responder.cpp"],"name":"_ZN9Responder11setSoftwareER7Message","regions":[[33,47,69,2,1,0,0,0],[44,20,44,25,5,0,0,0],[44,27,44,30,4,0,0,0],[44,31,44,32,4,0,0,3],[44,32,46,6,4,0,0,0]]},{"count":0,"filenames":["/Users/madslun/Documents/Programmering/U_look_stunning/stun/Responder.cpp"],"name":"_ZN9Responder12setXorAdressER7Message","regions":[[71,48,73,2,0,0,0,0]]},{"count":0,"filenames":["/Users/madslun/Documents/Programmering/U_look_stunning/stun/Responder.cpp"],"name":"_ZN9Responder16setHmacIntegrityER7Message","regions":[[75,52,77,2,0,0,0,0]]},{"count":0,"filenames":["/Users/madslun/Documents/Programmering/U_look_stunning/stun/Responder.cpp"],"name":"_ZN9Responder14setFingerprintER7Message","regions":[[79,50,81,2,0,0,0,0]]}],"totals":{"functions":{"count":39,"covered":13,"percent":33.333333333333329},"instantiations":{"count":39,"covered":13,"percent":33.333333333333329},"lines":{"count":418,"covered":205,"percent":49.043062200956939},"regions":{"count":82,"covered":29,"notcovered":53,"percent":35.365853658536587}}}],"type":"llvm.coverage.json.export","version":"2.0.0"}